[
  {
    "text": "hey",
    "intent": "greet",
    "intent_prediction": {
      "name": "affirm",
      "confidence": 0.05248502765026422
    }
  },
  {
    "text": "hello",
    "intent": "greet",
    "intent_prediction": {
      "name": "affirm",
      "confidence": 0.018966446987434313
    }
  },
  {
    "text": "hi",
    "intent": "greet",
    "intent_prediction": {
      "name": "affirm",
      "confidence": 0.07407518510233185
    }
  },
  {
    "text": "hello there",
    "intent": "greet",
    "intent_prediction": {
      "name": "affirm",
      "confidence": 0.0035216181277326667
    }
  },
  {
    "text": "good morning",
    "intent": "greet",
    "intent_prediction": {
      "name": "affirm",
      "confidence": 0.0060054233265864196
    }
  },
  {
    "text": "good evening",
    "intent": "greet",
    "intent_prediction": {
      "name": "affirm",
      "confidence": 0.005948900191420326
    }
  },
  {
    "text": "moin",
    "intent": "greet",
    "intent_prediction": {
      "name": "affirm",
      "confidence": 0.04578237814093846
    }
  },
  {
    "text": "hey there",
    "intent": "greet",
    "intent_prediction": {
      "name": "affirm",
      "confidence": 0.010618536650760508
    }
  },
  {
    "text": "let's go",
    "intent": "greet",
    "intent_prediction": {
      "name": "affirm",
      "confidence": 0.02692168330331598
    }
  },
  {
    "text": "hey dude",
    "intent": "greet",
    "intent_prediction": {
      "name": "affirm",
      "confidence": 0.024520569382615334
    }
  },
  {
    "text": "goodmorning",
    "intent": "greet",
    "intent_prediction": {
      "name": "affirm",
      "confidence": 0.007867756563109281
    }
  },
  {
    "text": "goodevening",
    "intent": "greet",
    "intent_prediction": {
      "name": "affirm",
      "confidence": 0.006718083272157892
    }
  },
  {
    "text": "good afternoon",
    "intent": "greet",
    "intent_prediction": {
      "name": "affirm",
      "confidence": 0.008705950551295237
    }
  },
  {
    "text": "cu",
    "intent": "goodbye",
    "intent_prediction": {
      "name": "affirm",
      "confidence": 0.09613523845826404
    }
  },
  {
    "text": "good by",
    "intent": "goodbye",
    "intent_prediction": {
      "name": "affirm",
      "confidence": 0.030834152155753074
    }
  },
  {
    "text": "cee you later",
    "intent": "goodbye",
    "intent_prediction": {
      "name": "affirm",
      "confidence": 0.008710072910333351
    }
  },
  {
    "text": "good night",
    "intent": "goodbye",
    "intent_prediction": {
      "name": "affirm",
      "confidence": 0.01581438378181373
    }
  },
  {
    "text": "bye",
    "intent": "goodbye",
    "intent_prediction": {
      "name": "affirm",
      "confidence": 0.05081621402120367
    }
  },
  {
    "text": "goodbye",
    "intent": "goodbye",
    "intent_prediction": {
      "name": "affirm",
      "confidence": 0.021658436449688952
    }
  },
  {
    "text": "have a nice day",
    "intent": "goodbye",
    "intent_prediction": {
      "name": "affirm",
      "confidence": 0.0030705033544978586
    }
  },
  {
    "text": "see you around",
    "intent": "goodbye",
    "intent_prediction": {
      "name": "affirm",
      "confidence": 0.02889349914767129
    }
  },
  {
    "text": "bye bye",
    "intent": "goodbye",
    "intent_prediction": {
      "name": "affirm",
      "confidence": 0.000948465171887426
    }
  },
  {
    "text": "see you later",
    "intent": "goodbye",
    "intent_prediction": {
      "name": "affirm",
      "confidence": 0.009285390019856421
    }
  },
  {
    "text": "no",
    "intent": "deny",
    "intent_prediction": {
      "name": "affirm",
      "confidence": 0.028531462049348914
    }
  },
  {
    "text": "n",
    "intent": "deny",
    "intent_prediction": {
      "name": "affirm",
      "confidence": 0.062187185647739625
    }
  },
  {
    "text": "never",
    "intent": "deny",
    "intent_prediction": {
      "name": "affirm",
      "confidence": 0.020435108635528196
    }
  },
  {
    "text": "I don't think so",
    "intent": "deny",
    "intent_prediction": {
      "name": "affirm",
      "confidence": 0.0022938661961231094
    }
  },
  {
    "text": "don't like that",
    "intent": "deny",
    "intent_prediction": {
      "name": "affirm",
      "confidence": 0.01151051324971181
    }
  },
  {
    "text": "no way",
    "intent": "deny",
    "intent_prediction": {
      "name": "affirm",
      "confidence": 0.010486094705695604
    }
  },
  {
    "text": "not really",
    "intent": "deny",
    "intent_prediction": {
      "name": "affirm",
      "confidence": 0.008234499347778498
    }
  },
  {
    "text": "perfect",
    "intent": "mood_great",
    "intent_prediction": {
      "name": "affirm",
      "confidence": 0.05212906033168144
    }
  },
  {
    "text": "great",
    "intent": "mood_great",
    "intent_prediction": {
      "name": "affirm",
      "confidence": 0.058336172185611504
    }
  },
  {
    "text": "amazing",
    "intent": "mood_great",
    "intent_prediction": {
      "name": "affirm",
      "confidence": 0.024055650531606708
    }
  },
  {
    "text": "feeling like a king",
    "intent": "mood_great",
    "intent_prediction": {
      "name": "affirm",
      "confidence": 0.0005275756757378063
    }
  },
  {
    "text": "wonderful",
    "intent": "mood_great",
    "intent_prediction": {
      "name": "affirm",
      "confidence": 0.04131337883465942
    }
  },
  {
    "text": "I am feeling very good",
    "intent": "mood_great",
    "intent_prediction": {
      "name": "affirm",
      "confidence": 0.00029516635721909846
    }
  },
  {
    "text": "I am great",
    "intent": "mood_great",
    "intent_prediction": {
      "name": "affirm",
      "confidence": 0.004158033463761543
    }
  },
  {
    "text": "I am amazing",
    "intent": "mood_great",
    "intent_prediction": {
      "name": "affirm",
      "confidence": 0.001610477514170624
    }
  },
  {
    "text": "I am going to save the world",
    "intent": "mood_great",
    "intent_prediction": {
      "name": "affirm",
      "confidence": 9.97230526920069e-05
    }
  },
  {
    "text": "super stoked",
    "intent": "mood_great",
    "intent_prediction": {
      "name": "affirm",
      "confidence": 0.0276902018781601
    }
  },
  {
    "text": "extremely good",
    "intent": "mood_great",
    "intent_prediction": {
      "name": "affirm",
      "confidence": 0.015145978080821994
    }
  },
  {
    "text": "so so perfect",
    "intent": "mood_great",
    "intent_prediction": {
      "name": "affirm",
      "confidence": 0.0010768334706612493
    }
  },
  {
    "text": "so good",
    "intent": "mood_great",
    "intent_prediction": {
      "name": "affirm",
      "confidence": 0.054936027672605525
    }
  },
  {
    "text": "so perfect",
    "intent": "mood_great",
    "intent_prediction": {
      "name": "affirm",
      "confidence": 0.007487002000261502
    }
  },
  {
    "text": "my day was horrible",
    "intent": "mood_unhappy",
    "intent_prediction": {
      "name": "affirm",
      "confidence": 0.011377929124564761
    }
  },
  {
    "text": "I am sad",
    "intent": "mood_unhappy",
    "intent_prediction": {
      "name": "affirm",
      "confidence": 0.003987194431043112
    }
  },
  {
    "text": "I don't feel very well",
    "intent": "mood_unhappy",
    "intent_prediction": {
      "name": "affirm",
      "confidence": 0.0008536140841404604
    }
  },
  {
    "text": "I am disappointed",
    "intent": "mood_unhappy",
    "intent_prediction": {
      "name": "affirm",
      "confidence": 0.0068118748439616635
    }
  },
  {
    "text": "super sad",
    "intent": "mood_unhappy",
    "intent_prediction": {
      "name": "affirm",
      "confidence": 0.006265623466507737
    }
  },
  {
    "text": "I'm so sad",
    "intent": "mood_unhappy",
    "intent_prediction": {
      "name": "affirm",
      "confidence": 0.0014485127245746322
    }
  },
  {
    "text": "sad",
    "intent": "mood_unhappy",
    "intent_prediction": {
      "name": "affirm",
      "confidence": 0.04960810471179882
    }
  },
  {
    "text": "very sad",
    "intent": "mood_unhappy",
    "intent_prediction": {
      "name": "affirm",
      "confidence": 0.0068092527559247265
    }
  },
  {
    "text": "unhappy",
    "intent": "mood_unhappy",
    "intent_prediction": {
      "name": "affirm",
      "confidence": 0.048200115625219364
    }
  },
  {
    "text": "not good",
    "intent": "mood_unhappy",
    "intent_prediction": {
      "name": "affirm",
      "confidence": 0.036892661092381006
    }
  },
  {
    "text": "not very good",
    "intent": "mood_unhappy",
    "intent_prediction": {
      "name": "affirm",
      "confidence": 0.006083904796111388
    }
  },
  {
    "text": "extremly sad",
    "intent": "mood_unhappy",
    "intent_prediction": {
      "name": "affirm",
      "confidence": 0.012267990748574962
    }
  },
  {
    "text": "so saad",
    "intent": "mood_unhappy",
    "intent_prediction": {
      "name": "affirm",
      "confidence": 0.020254244000107526
    }
  },
  {
    "text": "so sad",
    "intent": "mood_unhappy",
    "intent_prediction": {
      "name": "affirm",
      "confidence": 0.014231633116286444
    }
  },
  {
    "text": "are you a bot?",
    "intent": "bot_challenge",
    "intent_prediction": {
      "name": "affirm",
      "confidence": 0.002009268900788376
    }
  },
  {
    "text": "are you a human?",
    "intent": "bot_challenge",
    "intent_prediction": {
      "name": "affirm",
      "confidence": 0.0007210892581498259
    }
  },
  {
    "text": "am I talking to a bot?",
    "intent": "bot_challenge",
    "intent_prediction": {
      "name": "affirm",
      "confidence": 6.207006150035119e-05
    }
  },
  {
    "text": "am I talking to a human?",
    "intent": "bot_challenge",
    "intent_prediction": {
      "name": "affirm",
      "confidence": 2.2018088772652378e-05
    }
  }
]